{"date":"2025-04-27T19:38:03Z","workouts":[{"activityType":"Functional Strength Training","startDate":"2025-04-25T19:33:13Z","device":"Apple Watch","duration":914.06390297412872,"weatherTemp_C":11.967285156247726,"totalEnergyBurned_kcal":97.690982825081008,"weatherHumidity_pct":87,"uuid":"E004FD77-8C0C-4124-8F96-02AAF8E2D3A6","endDate":"2025-04-25T19:48:27Z"},{"activityType":"Running","totalEnergyBurned_kcal":350.44965588507563,"device":"Apple Watch","duration":6339.458468914032,"endDate":"2025-04-25T19:26:34Z","startDate":"2025-04-25T17:40:54Z","elevationAscended_m":2.75,"weatherHumidity_pct":83,"uuid":"53FBEF05-870D-4DF2-B47E-9E2FF8EF9DB5","totalDistance_m":5088.5249180442843,"weatherTemp_C":12.940072059629074},{"totalEnergyBurned_kcal":72.330639147673054,"activityType":"Indoor Other (13)","uuid":"9145F5BC-AEA5-4E8E-9696-2DD271BC5EF5","startDate":"2025-04-24T17:34:23Z","duration":504.41300892829895,"endDate":"2025-04-24T17:42:47Z","weatherTemp_C":12.496805191037765,"device":"Apple Watch","weatherHumidity_pct":79},{"device":"Apple Watch","totalEnergyBurned_kcal":53.653796452002283,"weatherHumidity_pct":79,"duration":496.08817708492279,"endDate":"2025-04-24T17:34:17Z","startDate":"2025-04-24T17:24:48Z","activityType":"Indoor Rowing","uuid":"351F023E-5EBA-45C7-AA19-3732BB232BA8","weatherTemp_C":12.577297210691086},{"totalDistance_m":2948.6390790203586,"duration":3738.3382869958878,"uuid":"15C97ECD-DCE5-4547-8F6A-1CD30BFC6A8C","endDate":"2025-04-23T17:57:44Z","device":"Apple Watch","activityType":"Running","totalEnergyBurned_kcal":185.34494238023888,"startDate":"2025-04-23T16:55:26Z","weatherTemp_C":13.52633953094255,"weatherHumidity_pct":69},{"totalEnergyBurned_kcal":85.517621893492944,"weatherTemp_C":13.024315834043136,"duration":747.38875496387482,"endDate":"2025-04-24T16:44:55Z","activityType":"Indoor Other (13)","startDate":"2025-04-24T16:32:28Z","uuid":"BCB7C886-6DE5-4792-884A-BE962F6F491D","weatherHumidity_pct":76,"device":"Apple Watch"},{"startDate":"2025-04-22T18:32:08Z","duration":841.64739596843719,"device":"Apple Watch","totalEnergyBurned_kcal":82.809999999999931,"activityType":"Indoor Other (13)","uuid":"6865253B-5D4D-486F-8C79-D8A10F2FEE30","weatherTemp_C":11.877339363095871,"weatherHumidity_pct":78,"endDate":"2025-04-22T18:46:10Z"},{"uuid":"FD761A3B-0E75-4A06-8A53-AEB47E7642C9","startDate":"2025-04-24T16:45:02Z","endDate":"2025-04-24T17:24:44Z","activityType":"Traditional Strength Training","duration":2381.910856962204,"device":"Apple Watch","weatherTemp_C":12.972834587094894,"weatherHumidity_pct":77,"effortScore":4,"totalEnergyBurned_kcal":212.07547307846446},{"totalEnergyBurned_kcal":98.193000000000296,"weatherTemp_C":11.614849090573898,"weatherHumidity_pct":79,"activityType":"Traditional Strength Training","startDate":"2025-04-22T18:46:15Z","device":"Apple Watch","endDate":"2025-04-22T19:02:28Z","uuid":"5B9D1519-D556-4112-93AA-0BBA0CF6A738","duration":973.38788306713104},{"totalDistance_m":3853.3494575708173,"endDate":"2025-04-22T18:21:01Z","activityType":"Running","weatherHumidity_pct":83,"weatherTemp_C":12.125734329221359,"duration":4906.5414808988571,"device":"Apple Watch","totalEnergyBurned_kcal":261.10436850962463,"effortScore":3,"startDate":"2025-04-22T16:59:15Z","uuid":"6DB09B23-600C-41FF-B3D6-13D93EC5AB0B"},{"device":"Apple Watch","uuid":"73FE878F-B72D-4EDF-A846-0A0DD887F1A4","weatherHumidity_pct":60,"endDate":"2025-04-21T16:44:52Z","duration":550.3897008895874,"weatherTemp_C":12.826149940488449,"startDate":"2025-04-21T16:35:41Z","activityType":"Indoor Other (13)","totalEnergyBurned_kcal":95.853000000000023},{"totalEnergyBurned_kcal":120.479,"startDate":"2025-04-21T15:22:16Z","weatherTemp_C":13.381788253781906,"duration":943.10699701309204,"endDate":"2025-04-21T15:38:00Z","activityType":"Indoor Other (13)","uuid":"673F4C44-FD75-4259-89D9-C46D48464456","weatherHumidity_pct":61,"device":"Apple Watch"},{"totalEnergyBurned_kcal":382.61425101177775,"duration":3457.6770100593567,"endDate":"2025-04-21T16:35:40Z","device":"Apple Watch","weatherTemp_C":13.317034721372238,"uuid":"D0E750A5-BBBA-4983-993B-8063C0C2791A","startDate":"2025-04-21T15:38:02Z","activityType":"Traditional Strength Training","weatherHumidity_pct":61,"effortScore":5}]}