{"date":"2024-08-18","records":[{"value":0.0092400000000488949,"startDate":"2024-08-17T23:57:37Z","type":"HKQuantityTypeIdentifierDistanceWalkingRunning","unit":"km","endDate":"2024-08-17T23:57:42Z"},{"type":"HKQuantityTypeIdentifierDistanceWalkingRunning","unit":"km","endDate":"2024-08-18T06:57:59Z","value":0.014539999999979045,"startDate":"2024-08-18T06:57:52Z"},{"endDate":"2024-08-18T07:22:03Z","unit":"km","type":"HKQuantityTypeIdentifierDistanceWalkingRunning","value":0.10489999999996508,"startDate":"2024-08-18T07:14:37Z"},{"unit":"km","endDate":"2024-08-18T07:48:00Z","value":0.03147999999998137,"startDate":"2024-08-18T07:39:53Z","type":"HKQuantityTypeIdentifierDistanceWalkingRunning"},{"unit":"km","startDate":"2024-08-18T07:53:26Z","value":0.041759999999892897,"type":"HKQuantityTypeIdentifierDistanceWalkingRunning","endDate":"2024-08-18T08:00:27Z"},{"value":0.10695000000001165,"startDate":"2024-08-18T08:05:57Z","type":"HKQuantityTypeIdentifierDistanceWalkingRunning","unit":"km","endDate":"2024-08-18T08:15:19Z"},{"type":"HKQuantityTypeIdentifierDistanceWalkingRunning","unit":"km","startDate":"2024-08-18T08:16:41Z","value":0.12342999999999302,"endDate":"2024-08-18T08:26:00Z"},{"unit":"km","startDate":"2024-08-18T08:28:34Z","endDate":"2024-08-18T08:37:25Z","type":"HKQuantityTypeIdentifierDistanceWalkingRunning","value":0.054809999999823049},{"value":0.03263999999995576,"startDate":"2024-08-18T08:41:21Z","endDate":"2024-08-18T08:49:08Z","unit":"km","type":"HKQuantityTypeIdentifierDistanceWalkingRunning"},{"startDate":"2024-08-18T08:52:35Z","endDate":"2024-08-18T08:56:49Z","type":"HKQuantityTypeIdentifierDistanceWalkingRunning","unit":"km","value":0.06563000000006286},{"startDate":"2024-08-18T09:10:22Z","endDate":"2024-08-18T09:18:12Z","unit":"km","value":0.048970000000088477,"type":"HKQuantityTypeIdentifierDistanceWalkingRunning"},{"unit":"km","startDate":"2024-08-18T09:29:13Z","value":0.059999999999999998,"type":"HKQuantityTypeIdentifierDistanceWalkingRunning","endDate":"2024-08-18T09:30:35Z"},{"type":"HKQuantityTypeIdentifierDistanceWalkingRunning","endDate":"2024-08-18T10:02:18Z","startDate":"2024-08-18T09:59:37Z","value":0.071189999999944117,"unit":"km"},{"unit":"km","endDate":"2024-08-18T12:28:43Z","value":0.017369999999995344,"startDate":"2024-08-18T12:18:53Z","type":"HKQuantityTypeIdentifierDistanceWalkingRunning"},{"type":"HKQuantityTypeIdentifierDistanceWalkingRunning","startDate":"2024-08-18T12:30:33Z","unit":"km","endDate":"2024-08-18T12:30:46Z","value":0.01351999999996042},{"type":"HKQuantityTypeIdentifierDistanceWalkingRunning","endDate":"2024-08-18T14:25:49Z","value":0.0046799999999930153,"unit":"km","startDate":"2024-08-18T14:25:47Z"},{"startDate":"2024-08-18T16:26:12Z","type":"HKQuantityTypeIdentifierDistanceWalkingRunning","unit":"km","endDate":"2024-08-18T16:32:55Z","value":0.048570000000006983},{"value":0.060428249903605319,"startDate":"2024-08-18T16:47:24Z","type":"HKQuantityTypeIdentifierDistanceWalkingRunning","endDate":"2024-08-18T16:48:34Z","unit":"km"},{"endDate":"2024-08-18T17:43:27Z","value":0.062293012902431659,"type":"HKQuantityTypeIdentifierDistanceWalkingRunning","unit":"km","startDate":"2024-08-18T17:39:29Z"},{"startDate":"2024-08-18T17:58:40Z","unit":"km","endDate":"2024-08-18T17:58:43Z","type":"HKQuantityTypeIdentifierDistanceWalkingRunning","value":0.0055999999999767174},{"value":0.013679999999993015,"startDate":"2024-08-18T20:48:18Z","endDate":"2024-08-18T20:56:53Z","unit":"km","type":"HKQuantityTypeIdentifierDistanceWalkingRunning"},{"startDate":"2024-08-18T21:02:03Z","type":"HKQuantityTypeIdentifierDistanceWalkingRunning","unit":"km","endDate":"2024-08-18T21:02:29Z","value":0.033539999999979045},{"type":"HKQuantityTypeIdentifierDistanceWalkingRunning","startDate":"2024-08-18T22:57:47Z","endDate":"2024-08-18T22:57:50Z","unit":"km","value":0.0044000000000232829}],"type":"HKQuantityTypeIdentifierDistanceWalkingRunning"}